pgtask_worker/__init__.py
pgtask_worker/test_worker.py
pgtask_worker/utils.py
pgtask_worker-1.10.dist-info/DESCRIPTION.rst
pgtask_worker-1.10.dist-info/METADATA
pgtask_worker-1.10.dist-info/RECORD
pgtask_worker-1.10.dist-info/WHEEL
pgtask_worker-1.10.dist-info/metadata.json
pgtask_worker-1.10.dist-info/top_level.txt
