Metadata-Version: 2.0
Name: pgtask-worker
Version: 1.10
Summary: Worker library for Postgres pgtask event queue
Home-page: https://bitbucket.org/gclinch/pgtask
Author: Graham Clinch
Author-email: g.clinch@lancaster.ac.uk
License: Apache License, Version 2.0
Platform: UNKNOWN
Classifier: Development Status :: 5 - Production/Stable
Classifier: License :: OSI Approved :: Apache Software License
Classifier: Topic :: System :: Distributed Computing
Requires-Dist: psycopg2
